autoadd_bindir/__init__.py
autoadd_bindir/py.typed
autoadd_bindir-1.0.6.dist-info/METADATA
autoadd_bindir-1.0.6.dist-info/WHEEL
autoadd_bindir-1.0.6.dist-info/entry_points.txt
autoadd_bindir-1.0.6.dist-info/RECORD
