Metadata-Version: 2.1
Name: autoadd-bindir
Version: 1.0.6
Summary: Automatically add bin-dir to PATH for every process in your virtualenv.
Home-page: https://github.com/libranet/autoadd_bindir
License: MIT
Keywords: entrypoints,sitecustomize
Author: Wouter Vanden Hove
Author-email: wouter@libranet.eu
Maintainer: Wouter Vanden Hove
Maintainer-email: wouter@libranet.eu
Requires-Python: >=3.8.0
Classifier: Development Status :: 4 - Beta
Classifier: Environment :: Console
Classifier: Intended Audience :: Developers
Classifier: License :: OSI Approved :: MIT License
Classifier: Natural Language :: English
Classifier: Operating System :: POSIX :: Linux
Classifier: Programming Language :: Python :: 3
Classifier: Programming Language :: Python :: 3.8
Classifier: Programming Language :: Python :: 3.9
Classifier: Programming Language :: Python :: 3.10
Classifier: Programming Language :: Python :: 3.11
Classifier: Programming Language :: Python :: 3.10
Classifier: Programming Language :: Python :: 3.11
Classifier: Programming Language :: Python :: 3.8
Classifier: Programming Language :: Python :: 3.9
Classifier: Programming Language :: Python :: Implementation :: CPython
Classifier: Programming Language :: Python :: Implementation :: PyPy
Classifier: Topic :: Software Development
Classifier: Topic :: Software Development :: Libraries
Classifier: Typing :: Typed
Requires-Dist: sitecustomize-entrypoints (>=1.1)
Project-URL: Changelog, https://github.com/libranet/autoadd_bindir/releases
Project-URL: Documentation, https://autoadd-bindir.readthedocs.io
Project-URL: Issues, https://github.com/libranet/autoadd_bindir/issues
Project-URL: Repository, https://github.com/libranet/autoadd_bindir
